sayhello/__init__.py
sayhello/say_hello.py
my_pypi_package-0.0.2.dist-info/LICENSE.txt
my_pypi_package-0.0.2.dist-info/METADATA
my_pypi_package-0.0.2.dist-info/WHEEL
my_pypi_package-0.0.2.dist-info/top_level.txt
my_pypi_package-0.0.2.dist-info/RECORD
