Metadata-Version: 2.1
Name: my-pypi-package
Version: 0.0.2
Summary: my First Package
Home-page: https://github.com/frzmohammadali/my_pypi_package
Author: Mohammadali
Author-email: mforouzesh@mpi-sws.org
License: UNKNOWN
Platform: UNKNOWN
Classifier: Programming Language :: Python :: 3
Classifier: License :: OSI Approved :: MIT License
Classifier: Operating System :: OS Independent
Requires-Dist: numpy (>=1.17.0)
Requires-Dist: requests (>=2.22.0)
